ml_deploy/__init__.py
ml_deploy/errors.py
ml_deploy/main.py
ml_deploy/utils.py
ml_deploy/validators.py
ml_deploy/gunicorn/__init__.py
ml_deploy/gunicorn/app.py
ml_deploy/gunicorn/utils.py
ml_deploy/implements/__init__.py
ml_deploy/implements/base.py
ml_deploy/implements/pipeline.py
ml_deploy/implements/serving.py
ml_deploy/implements/training.py
ml_deploy/kafka/__init__.py
ml_deploy/kafka/utils.py
ml_deploy/metrics/__init__.py
ml_deploy/metrics/models.py
ml_deploy/metrics/server.py
ml_deploy/mlflow/__init__.py
ml_deploy/rest/__init__.py
ml_deploy/rest/utils.py
ml_deploy/validation/__init__.py
ml_deploy/validation/config.py
ml_deploy/validation/exceptions.py
ml_deploy/validation/pipeline.py
ml_deploy/validation/utils.py
ml_deploy/validation/validators.py
tests/test_implements/__init__.py
tests/test_implements/test_base.py
tests/test_implements/test_training.py
tests/test_metric/__init__.py
tests/test_metric/test_model.py
ml_deploy-2.0.0.dist-info/METADATA
ml_deploy-2.0.0.dist-info/WHEEL
ml_deploy-2.0.0.dist-info/entry_points.txt
ml_deploy-2.0.0.dist-info/top_level.txt
ml_deploy-2.0.0.dist-info/RECORD
